imaginepro/__init__.py
imaginepro/constants.py
imaginepro/sdk.py
imaginepro/types.py
imaginepro-0.1.0.dist-info/licenses/LICENSE
imaginepro-0.1.0.dist-info/METADATA
imaginepro-0.1.0.dist-info/WHEEL
imaginepro-0.1.0.dist-info/top_level.txt
imaginepro-0.1.0.dist-info/RECORD
