Metadata-Version: 2.4
Name: imaginepro
Version: 0.1.0
Summary: Official Python SDK for ImagineProAI image generation platform
Author-email: ImagineProAI Team <support@imaginepro.ai>
License: MIT License
Project-URL: Homepage, https://github.com/imaginpro/imaginepro-python-sdk
Project-URL: Bug Tracker, https://github.com/imaginpro/imaginepro-python-sdk/issues
Classifier: Programming Language :: Python :: 3
Classifier: Operating System :: OS Independent
Requires-Python: >=3.7
License-File: LICENSE
Requires-Dist: requests>=2.25.0
Dynamic: license-file
